slowpoke/__init__.py
slowpoke/cli.py
slowpoke/config.py
slowpoke/core.py
slowpoke/logger.py
slowpoke_flask-0.1.1.dist-info/licenses/LICENSE
slowpoke_flask-0.1.1.dist-info/METADATA
slowpoke_flask-0.1.1.dist-info/WHEEL
slowpoke_flask-0.1.1.dist-info/entry_points.txt
slowpoke_flask-0.1.1.dist-info/top_level.txt
slowpoke_flask-0.1.1.dist-info/RECORD
