Metadata-Version: 2.4
Name: slowpoke-flask
Version: 0.1.1
Summary: Track slow Flask routes and monitor bottlenecks
Author-email: Vedangi <vedangithokal@gmail.com>
Requires-Python: >=3.7
License-File: LICENSE
Requires-Dist: flask
Requires-Dist: click
Requires-Dist: tabulate
Provides-Extra: dev
Requires-Dist: pytest; extra == "dev"
Dynamic: license-file
